[
  {
    "name": "Addison",
    "id": "addison"
  },
  {
    "name": "Bennington",
    "id": "bennington"
  },
  {
    "name": "Caledonia",
    "id": "caledonia"
  },
  {
    "name": "Chittenden",
    "id": "chittenden"
  },
  {
    "name": "Essex",
    "id": "essex"
  },
  {
    "name": "Franklin",
    "id": "franklin"
  },
  {
    "name": "Grand Isle",
    "id": "grand isle"
  },
  {
    "name": "Lamoille",
    "id": "lamoille"
  },
  {
    "name": "Orange",
    "id": "orange"
  },
  {
    "name": "Orleans",
    "id": "orleans"
  },
  {
    "name": "Rutland",
    "id": "rutland"
  },
  {
    "name": "Washington",
    "id": "washington"
  },
  {
    "name": "Windham",
    "id": "windham"
  },
  {
    "name": "Windsor",
    "id": "windsor"
  }
]
